archival/__init__.py
archival/demo.py
archival-0.1.0.dist-info/METADATA
archival-0.1.0.dist-info/WHEEL
archival-0.1.0.dist-info/top_level.txt
archival-0.1.0.dist-info/RECORD
